{
  "cycle": 10,
  "pairs": {
    "['g1', 'g2']": [
      1,
      4,
      8
    ],
    "['br1', 'g1']": [
      1,
      4,
      8
    ],
    "['br1', 'g2']": [
      1,
      4,
      6,
      8
    ],
    "['b1', 'b2']": [
      2,
      9
    ],
    "['b1', 'br1']": [
      2,
      5,
      6
    ],
    "['b2', 'br1']": [
      2
    ],
    "['i1', 'i2']": [
      3,
      10
    ],
    "['i1', 'n1']": [
      3,
      7
    ],
    "['i2', 'n1']": [
      3
    ],
    "['b1', 'n1']": [
      5,
      9
    ],
    "['br1', 'n1']": [
      5
    ],
    "['b1', 'g2']": [
      6
    ],
    "['g1', 'i1']": [
      7
    ],
    "['g1', 'n1']": [
      7
    ],
    "['b2', 'n1']": [
      9
    ],
    "['g2', 'i1']": [
      10
    ],
    "['g2', 'i2']": [
      10
    ]
  },
  "links": [
    {
      "pair": "['g1', 'g2']",
      "cycle": 4,
      "count": 2
    },
    {
      "pair": "['br1', 'g1']",
      "cycle": 4,
      "count": 2
    },
    {
      "pair": "['br1', 'g2']",
      "cycle": 4,
      "count": 2
    },
    {
      "pair": "['b1', 'br1']",
      "cycle": 5,
      "count": 2
    },
    {
      "pair": "['i1', 'n1']",
      "cycle": 7,
      "count": 2
    },
    {
      "pair": "['b1', 'n1']",
      "cycle": 9,
      "count": 2
    }
  ]
}